roshtools/__init__.py
roshtools/files.py
roshtools/net.py
roshtools/strings.py
roshtools/timers.py
roshtools-0.1.5.dist-info/licenses/LICENSE.txt
roshtools-0.1.5.dist-info/METADATA
roshtools-0.1.5.dist-info/WHEEL
roshtools-0.1.5.dist-info/top_level.txt
roshtools-0.1.5.dist-info/RECORD
